json_streamer/__init__.py
json_streamer/json.py
json_streamer/parser.py
json_streamer-0.1.0.dist-info/LICENSE
json_streamer-0.1.0.dist-info/METADATA
json_streamer-0.1.0.dist-info/WHEEL
json_streamer-0.1.0.dist-info/top_level.txt
json_streamer-0.1.0.dist-info/RECORD
