Metadata-Version: 2.1
Name: json-streamer
Version: 0.1.0
Summary: A JSON parser capable of parsing incomplete JSON strings from streams/generators.
Author-email: Almog Baku <almog.baku@gmail.com>
License: MIT
Project-URL: Homepage, https://github.com/AlmogBaku/json-streamer
Project-URL: Bug Reports, https://github.com/AlmogBaku/json-streamer/issues
Project-URL: Source, https://github.com/AlmogBaku/json-streamer/
Keywords: json,stream,partial,generator
License-File: LICENSE
